lcp_delta/__init__.py
lcp_delta/global_helpers.py
lcp_delta/common/__init__.py
lcp_delta/common/api_endpoints.py
lcp_delta/common/api_helper_base.py
lcp_delta/common/constants.py
lcp_delta/common/credentials_holder.py
lcp_delta/common/http/exceptions.py
lcp_delta/common/http/retry_policies.py
lcp_delta/common/response_objects/usage_info.py
lcp_delta/enact/__init__.py
lcp_delta/enact/api_helper.py
lcp_delta/enact/base_endpoints.py
lcp_delta/enact/chart_helper.py
lcp_delta/enact/dps_helper.py
lcp_delta/enact/enums.py
lcp_delta/enact/helpers.py
lcp_delta/enact/loader.py
lcp_delta/enact/configs/__init__.py
lcp_delta/enact/configs/base_endpoints_default.py
lcp_delta/enact/configs/base_endpoints_dev.py
lcp_delta/enact/services/ancillary_service.py
lcp_delta/enact/services/bm_service.py
lcp_delta/enact/services/contract_evolution_service.py
lcp_delta/enact/services/day_ahead_service.py
lcp_delta/enact/services/epex_service.py
lcp_delta/enact/services/hof_service.py
lcp_delta/enact/services/index_service.py
lcp_delta/enact/services/leaderboard_service.py
lcp_delta/enact/services/news_table_service.py
lcp_delta/enact/services/nordpool_service.py
lcp_delta/enact/services/plant_service.py
lcp_delta/enact/services/series_service.py
lcp_delta/flextrack/__init__.py
lcp_delta/flextrack/api_helper.py
lcp_delta/flextrack/services/exporter_service.py
lcpdelta-2.1.20.dist-info/licenses/LICENSE
lcpdelta-2.1.20.dist-info/licenses/LICENSE-Apache
lcpdelta-2.1.20.dist-info/METADATA
lcpdelta-2.1.20.dist-info/WHEEL
lcpdelta-2.1.20.dist-info/top_level.txt
lcpdelta-2.1.20.dist-info/RECORD
