Metadata-Version: 2.4
Name: LCPDelta
Version: 2.1.20
Summary: LCPDelta Python Package
Author-email: LCP Delta <enact.helpdesk@lcp.uk.com>
Project-URL: Homepage, https://portal.lcpdelta.com/
Keywords: LCPDelta,Enact,Flextrack,Storetrack
Classifier: Programming Language :: Python :: 3
Classifier: License :: Other/Proprietary License
Classifier: Operating System :: OS Independent
Requires-Python: >=3.9
License-File: LICENSE
License-File: LICENSE-Apache
Requires-Dist: numpy
Requires-Dist: pandas
Requires-Dist: requests
Requires-Dist: signalrcore==0.9.5
Requires-Dist: matplotlib
Requires-Dist: httpx
Requires-Dist: tenacity
Provides-Extra: dev
Requires-Dist: pre-commit; extra == "dev"
Requires-Dist: ruff; extra == "dev"
Requires-Dist: pytest; extra == "dev"
Requires-Dist: pytest-mock; extra == "dev"
Requires-Dist: pytest-asyncio; extra == "dev"
Requires-Dist: python-dotenv; extra == "dev"
Requires-Dist: jupyter; extra == "dev"
Requires-Dist: nbval; extra == "dev"
Requires-Dist: pandas; extra == "dev"
Requires-Dist: numpy; extra == "dev"
Requires-Dist: signalrcore==0.9.5; extra == "dev"
Dynamic: license-file
